<beans xmlns="http://www.springframework.org/schema/beans"
       xmlns:xsi="http://www.w3.org/2001/XMLSchema-instance"
       xmlns:context="http://www.springframework.org/schema/context"
       xmlns:mvc="http://www.springframework.org/schema/mvc" xmlns:tx="http://www.springframework.org/schema/tx"
       xsi:schemaLocation="http://www.springframework.org/schema/beans
        http://www.springframework.org/schema/beans/spring-beans.xsd
        http://www.springframework.org/schema/context http://www.springframework.org/schema/context/spring-context.xsd http://www.springframework.org/schema/mvc http://www.springframework.org/schema/mvc/spring-mvc.xsd http://www.springframework.org/schema/tx http://www.springframework.org/schema/tx/spring-tx.xsd">

    <context:component-scan base-package="com.jiajiaohello"/>

    <bean id="placeholderConfigurer" class="org.springframework.beans.factory.config.PreferencesPlaceholderConfigurer">
        <!--
            Check system properties first, before trying the specified properties.
            This allows system properties to override any other property source.
        -->
        <property name="systemPropertiesMode" value="2" />
        <property name="location" value="classpath:server.properties" />
    </bean>

    <mvc:annotation-driven>
        <mvc:message-converters>
            <bean class="org.springframework.http.converter.StringHttpMessageConverter">
                <constructor-arg value="utf-8" />
                <property name="supportedMediaTypes">
                    <list>
                        <value>text/html;charset=UTF-8</value>
                        <value>text/plain;charset=UTF-8</value>
                    </list>
                </property>
            </bean>
            <bean class="org.springframework.http.converter.json.MappingJackson2HttpMessageConverter">
                <property name="supportedMediaTypes">
                    <list>
                        <value>text/json;charset=UTF-8</value>
                        <value>text/html;charset=UTF-8</value>
                        <value>text/plain;charset=UTF-8</value>
                    </list>
                </property>
            </bean>
        </mvc:message-converters>
    </mvc:annotation-driven>

    <bean id="multipartResolver" class="org.springframework.web.multipart.commons.CommonsMultipartResolver">
        <!-- one of the properties available; the maximum file size in bytes -->
        <property name="maxUploadSize" value="5242880000" />
        <property name="maxInMemorySize" value="512000" />
        <property name="defaultEncoding" value="UTF-8" />
    </bean>

    <bean class="org.springframework.web.servlet.view.InternalResourceViewResolver">
        <property name="prefix" value="/WEB-INF/pages/"/>
        <property name="suffix" value=".jsp"/>
    </bean>

    <mvc:resources mapping="/public/**" location="/public/"/>

    <bean id="dataSource" class="org.apache.commons.dbcp.BasicDataSource"
          destroy-method="close">
        <property name="driverClassName" value="${dataSource.driverClassName}" />
        <property name="url" value="${dataSource.url}" />
        <property name="username" value="${dataSource.username}" />
        <property name="password" value="${dataSource.password}" />
    </bean>

    <!-- Hibernate 4 SessionFactory Bean definition -->
    <bean id="hibernate4AnnotatedSessionFactory"
          class="org.springframework.orm.hibernate4.LocalSessionFactoryBean">
        <property name="dataSource" ref="dataSource" />
        <property name="packagesToScan" value="com.jiajiaohello" />
        <property name="hibernateProperties">
            <props>
                <prop key="hibernate.dialect">${hibernate.dialect}</prop>
                <prop key="hibernate.show_sql">${hibernate.show_sql}</prop>
                <prop key="hibernate.hbm2ddl.auto">${hibernate.hbm2ddl.auto}</prop>
            </props>
        </property>
        <property name="namingStrategy" ref="namingStrategy" />
    </bean>

    <bean id="namingStrategy" class="org.hibernate.cfg.ImprovedNamingStrategy" />

    <bean id="hibernateTemplate" class="org.springframework.orm.hibernate4.HibernateTemplate">
        <property name="sessionFactory" ref="hibernate4AnnotatedSessionFactory" />
        <!--<property name="cacheQueries" value="false" /> TODO product change to true-->
    </bean>
    <!-- SessionFactory, DataSource, etc. omitted -->

    <bean id="transactionManager"
          class="org.springframework.orm.hibernate4.HibernateTransactionManager">
        <property name="sessionFactory" ref="hibernate4AnnotatedSessionFactory"/>
    </bean>

    <tx:annotation-driven />

    <bean id="jedisPoolConfig" class="redis.clients.jedis.JedisPoolConfig">
        <property name="maxActive" value="50" />
        <property name="maxIdle" value="30" />
        <property name="minIdle" value="10" />
        <property name="maxWait" value="2000" />
    </bean>

    <!-- Jedis ConnectionFactory -->
    <bean id="jedisConnectionFactory" class="org.springframework.data.redis.connection.jedis.JedisConnectionFactory">
        <property name="timeout" value="5000" />
        <property name="poolConfig" ref="jedisPoolConfig" />
    </bean>

    <bean
            id="stringRedisSerializer"
            class="org.springframework.data.redis.serializer.StringRedisSerializer"/>

    <!-- redis template definition -->
    <bean id="redisTemplate" class="org.springframework.data.redis.core.RedisTemplate">
        <property name="connectionFactory" ref="jedisConnectionFactory" />
        <property name="keySerializer" ref="stringRedisSerializer" />
        <property name="hashKeySerializer" ref="stringRedisSerializer" />
    </bean>

    <bean id="ossClient" class="com.aliyun.openservices.oss.OSSClient">
        <constructor-arg name="endpoint" value="http://${ossClient.endpoint.domain}" />
        <constructor-arg name="accessKeyId" value="${ossClient.accessKeyId}" />
        <constructor-arg name="accessKeySecret" value="${ossClient.accessKeySecret}" />
    </bean>
</beans>